_xpress.cp313-win_amd64.pyd
xpress/__init__.py
xpress/__version_file__.py
xpress/constants.py
xpress/enums.py
xpress/numpy_.py
xpress/pandas_.py
xpress/examples/README.txt
xpress/examples/index.xml
xpress/examples/modeling_examples/benders_decomp.py
xpress/examples/modeling_examples/blend.py
xpress/examples/modeling_examples/blend2.py
xpress/examples/modeling_examples/burglar.py
xpress/examples/modeling_examples/burglar_rec.py
xpress/examples/modeling_examples/burglari.py
xpress/examples/modeling_examples/burglarl.py
xpress/examples/modeling_examples/catenary.py
xpress/examples/modeling_examples/chess.py
xpress/examples/modeling_examples/chess2.py
xpress/examples/modeling_examples/coco.py
xpress/examples/modeling_examples/crudeoil_pooling.py
xpress/examples/modeling_examples/cuttingstock.py
xpress/examples/modeling_examples/facility_location_pandas.py
xpress/examples/modeling_examples/feas_pump.py
xpress/examples/modeling_examples/firestation_scipy.py
xpress/examples/modeling_examples/fstns.py
xpress/examples/modeling_examples/gencons_pbo.py
xpress/examples/modeling_examples/gencons_sat.py
xpress/examples/modeling_examples/goalprog.py
xpress/examples/modeling_examples/inscribedsquare.py
xpress/examples/modeling_examples/knapsack.py
xpress/examples/modeling_examples/markowitz.py
xpress/examples/modeling_examples/maxSumLogistic.py
xpress/examples/modeling_examples/multicommodity_flow.py
xpress/examples/modeling_examples/multiobjknapsack.py
xpress/examples/modeling_examples/n_queens.py
xpress/examples/modeling_examples/netflow.py
xpress/examples/modeling_examples/polygon.py
xpress/examples/modeling_examples/pplan.py
xpress/examples/modeling_examples/pwl_transp.py
xpress/examples/modeling_examples/sudoku.py
xpress/examples/modeling_examples/trans.py
xpress/examples/modeling_examples/tsp.py
xpress/examples/modeling_examples/tsp_numpy.py
xpress/examples/modeling_examples/Data/blend_data.py
xpress/examples/modeling_examples/Data/burglar_rec_dat.py
xpress-9.8.0.dist-info/licenses/LICENSE.txt
xpress-9.8.0.dist-info/METADATA
xpress-9.8.0.dist-info/WHEEL
xpress-9.8.0.dist-info/top_level.txt
xpress-9.8.0.dist-info/RECORD
