Metadata-Version: 2.4
Name: xpress
Version: 9.8.0
Summary: FICO Xpress Optimizer Python interface
Home-page: https://www.fico.com/en/products/fico-xpress-optimization
Author: FICO Xpress Optimizer dev. team
Author-email: support@fico.com
Keywords: optimization mip minlp xpress
Platform: any
Classifier: Development Status :: 5 - Production/Stable
Classifier: Intended Audience :: Science/Research
Classifier: Intended Audience :: Developers
Classifier: Programming Language :: C
Classifier: Programming Language :: C++
Classifier: Programming Language :: Python
Classifier: Programming Language :: Python :: 3
Classifier: Programming Language :: Python :: 3.9
Classifier: Programming Language :: Python :: 3.10
Classifier: Programming Language :: Python :: 3.11
Classifier: Programming Language :: Python :: 3.12
Classifier: Topic :: Software Development
Classifier: Topic :: Scientific/Engineering
Classifier: Operating System :: Microsoft :: Windows
Classifier: Operating System :: POSIX :: Linux
Classifier: Operating System :: MacOS
Classifier: License :: Other/Proprietary License
License-File: LICENSE.txt
Requires-Dist: numpy>=1.19
Requires-Dist: xpresslibs==9.8.0
Provides-Extra: cuda
Requires-Dist: cuda-toolkit[cublas,cudart,cusparse]<13.1,>=13.0.1; extra == "cuda"
Dynamic: author
Dynamic: author-email
Dynamic: classifier
Dynamic: description
Dynamic: description-content-type
Dynamic: home-page
Dynamic: keywords
Dynamic: license-file
Dynamic: platform
Dynamic: provides-extra
Dynamic: requires-dist
Dynamic: summary
